{"gameId":432,"fileName":"lootjs-forge-1.19.2-2.9.1.jar","gameVersions":["1.19.2","Forge"],"displayName":"LootJS-Forge-1.19.2-2.9.1","sortableGameVersions":[{"gameVersionPadded":"0000000001.0000000019.0000000002","gameVersion":"1.19.2","gameVersionReleaseDate":"2022-08-05T14:12:22.413Z","gameVersionName":"1.19.2","gameVersionTypeId":73407},{"gameVersionPadded":"0","gameVersion":"","gameVersionReleaseDate":"2022-10-01T00:00:00Z","gameVersionName":"Forge","gameVersionTypeId":68441}],"downloadUrl":"https://edge.forgecdn.net/files/4709/99/lootjs-forge-1.19.2-2.9.1.jar","fileDate":"2023-08-17T12:32:59.873Z","exposeAsAlternative":null,"modId":570630,"modules":[{"name":"META-INF","fingerprint":867948004},{"name":"architectury.common.json","fingerprint":118629613},{"name":"kubejs.plugins.txt","fingerprint":1593166766},{"name":"lootjs-common.mixins.json","fingerprint":3245851737},{"name":"lootjs-common-1.19.2-common-refmap.json","fingerprint":4242388510},{"name":"lootjs-forge.mixins.json","fingerprint":3985952806},{"name":"pack.mcmeta","fingerprint":692389130},{"name":"data","fingerprint":2312894697},{"name":"lootjs-forge-1.19.2-forge-refmap.json","fingerprint":1493072104},{"name":"com","fingerprint":3451191733},{"name":"architectury_inject_LootJS_common_086a2bf40a48414bacd522fc08fff69c_ee28fcd33acf35396e85aa0c5495c544c658bcda9cf3134fbc8ae77ea8cd0df7lootjscommon1192291devjar","fingerprint":8006040}],"dependencies":[{"relationType":3,"modId":238086}],"fileFingerprint":3887243245,"fileStatus":4,"releaseType":1,"hashes":[{"value":"73d4569729843e1838d15aa0d63f933318d76790","algo":1},{"value":"5d5f461a03ec9bc34b9e0b1b676e354d","algo":2}],"parentProjectFileId":null,"alternateFileId":0,"id":4709099,"fileLength":237091,"downloadCount":790737,"serverPackFileId":null,"available":false,"serverPack":false}