{"gameId":432,"fileName":"balm-forge-1.19.2-4.6.0.jar","gameVersions":["1.19.2","Forge","1.19.1","1.19"],"displayName":"balm-forge-1.19.2-4.6.0.jar","sortableGameVersions":[{"gameVersionPadded":"0000000001.0000000019.0000000002","gameVersion":"1.19.2","gameVersionReleaseDate":"2022-08-05T14:12:22.413Z","gameVersionName":"1.19.2","gameVersionTypeId":73407},{"gameVersionPadded":"0","gameVersion":"","gameVersionReleaseDate":"2022-10-01T00:00:00Z","gameVersionName":"Forge","gameVersionTypeId":68441},{"gameVersionPadded":"0000000001.0000000019.0000000001","gameVersion":"1.19.1","gameVersionReleaseDate":"2022-06-28T00:00:00Z","gameVersionName":"1.19.1","gameVersionTypeId":73407},{"gameVersionPadded":"0000000001.0000000019","gameVersion":"1.19","gameVersionReleaseDate":"2022-06-07T15:38:07.377Z","gameVersionName":"1.19","gameVersionTypeId":73407}],"downloadUrl":"https://edge.forgecdn.net/files/4751/735/balm-forge-1.19.2-4.6.0.jar","fileDate":"2023-09-14T10:22:26.567Z","exposeAsAlternative":null,"modId":531761,"modules":[{"name":"META-INF","fingerprint":2055122763},{"name":"net","fingerprint":3608397381},{"name":"balm-icon.png","fingerprint":3535347704},{"name":"balm.mixins.json","fingerprint":1019442043},{"name":"data","fingerprint":3455063956},{"name":"pack.mcmeta","fingerprint":2769305621},{"name":"balm.refmap.json","fingerprint":3112077964}],"dependencies":[],"fileFingerprint":1779860652,"fileStatus":4,"releaseType":1,"hashes":[{"value":"26e05173447e692783eb6a92197f6bf45d894e54","algo":1},{"value":"009bdfde01e742c98cfe71babbd58fce","algo":2}],"parentProjectFileId":null,"alternateFileId":0,"id":4751735,"fileLength":314084,"downloadCount":8906493,"serverPackFileId":null,"available":false,"serverPack":false}