{"gameId":432,"fileName":"tinker_io-1.12.2-rw2.8.3.jar","gameVersions":["1.12.2"],"displayName":"tinker_io-1.12.2-rw2.8.3","sortableGameVersions":[{"gameVersionPadded":"0000000001.0000000012.0000000002","gameVersion":"1.12.2","gameVersionReleaseDate":"2017-09-18T05:00:00Z","gameVersionName":"1.12.2","gameVersionTypeId":628}],"downloadUrl":"https://edge.forgecdn.net/files/3102/626/tinker_io-1.12.2-rw2.8.3.jar","fileDate":"2020-11-05T03:29:46.470Z","exposeAsAlternative":null,"modId":229503,"modules":[{"name":"META-INF","fingerprint":2406129441},{"name":"tinker_io","fingerprint":3355015645},{"name":"assets","fingerprint":1106340007},{"name":"logo.png","fingerprint":4293701413},{"name":"mcmod.info","fingerprint":2301735938}],"dependencies":[{"relationType":3,"modId":74072}],"fileFingerprint":3882346848,"fileStatus":4,"releaseType":1,"hashes":[{"value":"6fe015e930d57f3c9b4c41731f6464d55a198f72","algo":1},{"value":"4736bd776d4fbbdf3324cc11a249cc6b","algo":2}],"parentProjectFileId":null,"alternateFileId":0,"id":3102626,"fileLength":5770361,"downloadCount":1652903,"serverPackFileId":null,"serverPack":false,"available":false}