{"gameId":432,"fileName":"chiselsandbits-14.33.jar","gameVersions":["1.12.1","1.12","1.12.2"],"displayName":"chiselsandbits-14.33.jar","sortableGameVersions":[{"gameVersionPadded":"0000000001.0000000012.0000000001","gameVersion":"1.12.1","gameVersionReleaseDate":"2017-08-03T05:00:00Z","gameVersionName":"1.12.1","gameVersionTypeId":628},{"gameVersionPadded":"0000000001.0000000012","gameVersion":"1.12","gameVersionReleaseDate":"2017-06-07T05:00:00Z","gameVersionName":"1.12","gameVersionTypeId":628},{"gameVersionPadded":"0000000001.0000000012.0000000002","gameVersion":"1.12.2","gameVersionReleaseDate":"2017-09-18T05:00:00Z","gameVersionName":"1.12.2","gameVersionTypeId":628}],"downloadUrl":"https://edge.forgecdn.net/files/2720/655/chiselsandbits-14.33.jar","fileDate":"2019-06-06T01:32:08.750Z","exposeAsAlternative":null,"modId":231095,"modules":[{"name":"META-INF","fingerprint":2066040898},{"name":"mod","fingerprint":3608985086},{"name":"assets","fingerprint":321139769},{"name":"mcmod.info","fingerprint":3876564513},{"name":"pack.mcmeta","fingerprint":2325622583}],"dependencies":[{"relationType":2,"modId":238222},{"relationType":2,"modId":239431}],"fileFingerprint":3211462819,"fileStatus":4,"releaseType":1,"hashes":[{"value":"0e6f159254e6899651087e5b1464bac91698d1d3","algo":1},{"value":"e056e23559965f2ebabf47aad0fe51a3","algo":2}],"parentProjectFileId":null,"alternateFileId":0,"id":2720655,"fileLength":737407,"downloadCount":39871134,"serverPackFileId":null,"serverPack":false,"available":false}