{"gameId":432,"fileName":"RandomThings-MC1.12.2-4.2.7.4.jar","gameVersions":["Forge","1.12.2"],"displayName":"RandomThings-MC1.12.2-4.2.7.4.jar","sortableGameVersions":[{"gameVersionPadded":"0","gameVersion":"","gameVersionReleaseDate":"2022-10-01T00:00:00Z","gameVersionName":"Forge","gameVersionTypeId":68441},{"gameVersionPadded":"0000000001.0000000012.0000000002","gameVersion":"1.12.2","gameVersionReleaseDate":"2017-09-18T05:00:00Z","gameVersionName":"1.12.2","gameVersionTypeId":628}],"downloadUrl":"https://edge.forgecdn.net/files/2905/241/RandomThings-MC1.12.2-4.2.7.4.jar","fileDate":"2020-03-19T09:59:02.387Z","exposeAsAlternative":null,"modId":59816,"modules":[{"name":"META-INF","fingerprint":2446870168},{"name":"assets","fingerprint":1803087542},{"name":"info","fingerprint":1136138571},{"name":"logo.png","fingerprint":757386000},{"name":"lumien","fingerprint":2115948452},{"name":"mcmod.info","fingerprint":3634089514},{"name":"pack.mcmeta","fingerprint":1689688708}],"dependencies":[],"fileFingerprint":3215073064,"fileStatus":4,"releaseType":1,"hashes":[{"value":"4422c297678e8f07a476ca5d4972568cfc7576bb","algo":1},{"value":"b91502e1810cdf13dfd5fb3b4e15e5ad","algo":2}],"parentProjectFileId":null,"alternateFileId":0,"id":2905241,"fileLength":3292861,"downloadCount":13850665,"serverPackFileId":null,"serverPack":false,"available":false}