{"allowModDistribution":true,"screenshots":[],"classId":6,"latestFilesIndexes":[{"filename":"LibVulpes-1.12.2-0.4.2-25-universal.jar","releaseType":1,"gameVersion":"1.12.2","gameVersionTypeId":628,"modLoader":null,"fileId":3801015},{"filename":"LibVulpes-1.12.2-0.4.2-24-universal.jar","releaseType":2,"gameVersion":"1.12.2","gameVersionTypeId":628,"modLoader":null,"fileId":3775180},{"filename":"LibVulpes-1.16.5-1.0.2-1-universal.jar","releaseType":3,"gameVersion":"1.16.5","gameVersionTypeId":70886,"modLoader":1,"fileId":3499785},{"filename":"LibVulpes-1.7.10-0.2.8-37-universal.jar","releaseType":3,"gameVersion":"1.7.10","gameVersionTypeId":5,"modLoader":null,"fileId":2812784},{"filename":"LibVulpes-1.11.2-0.2.8-37-universal.jar","releaseType":3,"gameVersion":"1.11.2","gameVersionTypeId":599,"modLoader":null,"fileId":2558981},{"filename":"LibVulpes-1.10.2-0.2.8-37-universal.jar","releaseType":3,"gameVersion":"1.10.2","gameVersionTypeId":572,"modLoader":null,"fileId":2558976}],"dateCreated":"2015-09-29T06:51:33.52Z","logo":{"description":"","id":26403,"title":"635790882935348135.png","modId":236541,"url":"https://media.forgecdn.net/avatars/26/403/635790882935348135.png","thumbnailUrl":"https://media.forgecdn.net/avatars/thumbnails/26/403/256/256/635790882935348135.png"},"links":{"sourceUrl":"https://github.com/zmaster587/LibVulpes","issuesUrl":null,"websiteUrl":"https://www.curseforge.com/minecraft/mc-mods/libvulpes","wikiUrl":""},"dateReleased":"2022-05-22T08:48:22.527Z","id":236541,"categories":[{"gameId":432,"classId":6,"name":"API and Library","dateModified":"2014-05-23T03:21:44.06Z","parentCategoryId":6,"id":421,"iconUrl":"https://media.forgecdn.net/avatars/6/36/635351496947765531.png","slug":"library-api","url":"https://www.curseforge.com/minecraft/mc-mods/library-api","displayIndex":0,"class":false}],"slug":"libvulpes","gameId":432,"summary":"Common Library required for my mods","latestFiles":[{"gameId":432,"fileName":"LibVulpes-1.7.10-0.2.8-37-universal.jar","gameVersions":["1.7.10"],"displayName":"LibVulpes 1.7.10-0.2.8-37-UNSTABLE build -37 for 1.7.10","sortableGameVersions":[{"gameVersionPadded":"0000000001.0000000007.0000000010","gameVersion":"1.7.10","gameVersionReleaseDate":"2014-06-16T00:00:00Z","gameVersionName":"1.7.10","gameVersionTypeId":5}],"downloadUrl":"https://edge.forgecdn.net/files/2812/784/LibVulpes-1.7.10-0.2.8-37-universal.jar","fileDate":"2019-10-20T01:30:46.317Z","exposeAsAlternative":null,"modId":236541,"modules":[{"name":"META-INF","fingerprint":605147677},{"name":"zmaster587","fingerprint":2148403795},{"name":"cofh","fingerprint":4103990547},{"name":"assets","fingerprint":4188000423},{"name":"mcmod.info","fingerprint":3154697132}],"dependencies":[],"fileFingerprint":419509130,"fileStatus":4,"releaseType":3,"hashes":[{"value":"096ae9fd15612d589cdf2aff45fd45740dfd6eb9","algo":1},{"value":"7d925a30b25a94b5a6a6bfe9e35ccc66","algo":2}],"parentProjectFileId":null,"alternateFileId":0,"id":2812784,"fileLength":385062,"downloadCount":125779,"serverPackFileId":null,"serverPack":false,"available":false},{"gameId":432,"fileName":"LibVulpes-1.16.5-1.0.2-1-universal.jar","gameVersions":["1.16.5","Forge"],"displayName":"LibVulpes 1.16.5-1.0.2-1 build -1 for 1.16.5","sortableGameVersions":[{"gameVersionPadded":"0000000001.0000000016.0000000005","gameVersion":"1.16.5","gameVersionReleaseDate":"2021-01-15T14:14:48.91Z","gameVersionName":"1.16.5","gameVersionTypeId":70886},{"gameVersionPadded":"0","gameVersion":"","gameVersionReleaseDate":"2022-10-01T00:00:00Z","gameVersionName":"Forge","gameVersionTypeId":68441}],"downloadUrl":"https://edge.forgecdn.net/files/3499/785/LibVulpes-1.16.5-1.0.2-1-universal.jar","fileDate":"2021-10-23T04:08:32.520Z","exposeAsAlternative":null,"modId":236541,"modules":[{"name":"META-INF","fingerprint":703975427},{"name":"zmaster587","fingerprint":2377822189},{"name":"data","fingerprint":3766360877},{"name":"pack.mcmeta","fingerprint":2862045449},{"name":"assets","fingerprint":2443608644},{"name":"mcmod.info","fingerprint":629858128}],"dependencies":[],"fileFingerprint":1516527202,"fileStatus":4,"releaseType":3,"hashes":[{"value":"debbc76fdbf9f4683df380e089f31ba97219c84a","algo":1},{"value":"20ce0610513233bbeb523f585d49d89a","algo":2}],"parentProjectFileId":null,"alternateFileId":0,"id":3499785,"fileLength":650127,"downloadCount":177205,"serverPackFileId":null,"serverPack":false,"available":false},{"gameId":432,"fileName":"LibVulpes-1.12.2-0.4.2-24-universal.jar","gameVersions":["1.12.2"],"displayName":"LibVulpes 1.12.2-0.4.2-24 build -24 for 1.12.2","sortableGameVersions":[{"gameVersionPadded":"0000000001.0000000012.0000000002","gameVersion":"1.12.2","gameVersionReleaseDate":"2017-09-18T05:00:00Z","gameVersionName":"1.12.2","gameVersionTypeId":628}],"downloadUrl":"https://edge.forgecdn.net/files/3775/180/LibVulpes-1.12.2-0.4.2-24-universal.jar","fileDate":"2022-04-30T19:51:02.507Z","exposeAsAlternative":null,"modId":236541,"modules":[{"name":"META-INF","fingerprint":3527875583},{"name":"zmaster587","fingerprint":1583817609},{"name":"assets","fingerprint":3364753046},{"name":"mcmod.info","fingerprint":4102694476}],"dependencies":[],"fileFingerprint":1740544607,"fileStatus":4,"releaseType":2,"hashes":[{"value":"0900e3493339f06615b1413e8aa8624842237e25","algo":1},{"value":"fb74c6a9add486d4317ab8e92113974e","algo":2}],"parentProjectFileId":null,"alternateFileId":0,"id":3775180,"fileLength":539301,"downloadCount":16078,"serverPackFileId":null,"serverPack":false,"available":false},{"gameId":432,"fileName":"LibVulpes-1.12.2-0.4.2-25-universal.jar","gameVersions":["1.12.2"],"displayName":"LibVulpes 1.12.2-0.4.2-25 build -25 for 1.12.2","sortableGameVersions":[{"gameVersionPadded":"0000000001.0000000012.0000000002","gameVersion":"1.12.2","gameVersionReleaseDate":"2017-09-18T05:00:00Z","gameVersionName":"1.12.2","gameVersionTypeId":628}],"downloadUrl":"https://edge.forgecdn.net/files/3801/15/LibVulpes-1.12.2-0.4.2-25-universal.jar","fileDate":"2022-05-22T08:48:22.107Z","exposeAsAlternative":null,"modId":236541,"modules":[{"name":"META-INF","fingerprint":2184030009},{"name":"zmaster587","fingerprint":1817528630},{"name":"assets","fingerprint":3364753046},{"name":"mcmod.info","fingerprint":989005462}],"dependencies":[],"fileFingerprint":429175792,"fileStatus":4,"releaseType":1,"hashes":[{"value":"bb81db439fd13ce086e822cd5c31505543487b58","algo":1},{"value":"f5b3a43fd2f82ec39ad04e5392079d6e","algo":2}],"parentProjectFileId":null,"alternateFileId":0,"id":3801015,"fileLength":539301,"downloadCount":751260,"serverPackFileId":null,"serverPack":false,"available":false}],"dateModified":"2022-05-22T08:53:24.54Z","gamePopularityRank":2434,"thumbsUpCount":0,"name":"LibVulpes","mainFileId":3801015,"primaryCategoryId":421,"downloadCount":20581955,"status":4,"authors":[{"name":"zmaster587","id":9136874,"url":"https://www.curseforge.com/members/zmaster587"}],"available":false,"featured":false}