{"allowModDistribution":true,"screenshots":[{"description":"","id":443057,"title":"Redstone Logic Controller - GUI","modId":461710,"url":"https://media.forgecdn.net/attachments/443/57/redstone-logic-control-2.png","thumbnailUrl":"https://media.forgecdn.net/attachments/thumbnails/443/57/310/172/redstone-logic-control-2.png"},{"description":"","id":371349,"title":"Bridging Relay wall mount","modId":461710,"url":"https://media.forgecdn.net/attachments/371/349/bridging-relay.png","thumbnailUrl":"https://media.forgecdn.net/attachments/thumbnails/371/349/310/172/bridging-relay.png"},{"description":"","id":357106,"title":"Relay Recipes","modId":461710,"url":"https://media.forgecdn.net/attachments/357/106/2021-04-18-relay-recipe1.png","thumbnailUrl":"https://media.forgecdn.net/attachments/thumbnails/357/106/310/172/2021-04-18-relay-recipe1.png"},{"description":"","id":369556,"title":"Bridging Relay","modId":461710,"url":"https://media.forgecdn.net/attachments/369/556/redstonepen-bridge-relay.png","thumbnailUrl":"https://media.forgecdn.net/attachments/thumbnails/369/556/310/172/redstonepen-bridge-relay.png"},{"description":"","id":355350,"title":"Pen Recipe","modId":461710,"url":"https://media.forgecdn.net/attachments/355/350/rspen-penrecipe.png","thumbnailUrl":"https://media.forgecdn.net/attachments/thumbnails/355/350/310/172/rspen-penrecipe.png"},{"description":"","id":350646,"title":"Example track routing","modId":461710,"url":"https://media.forgecdn.net/attachments/350/646/pentracks.png","thumbnailUrl":"https://media.forgecdn.net/attachments/thumbnails/350/646/310/172/pentracks.png"},{"description":"","id":357105,"title":"Pen/Quill 3rd person","modId":461710,"url":"https://media.forgecdn.net/attachments/357/105/2021-04-18-wilepen.png","thumbnailUrl":"https://media.forgecdn.net/attachments/thumbnails/357/105/310/172/2021-04-18-wilepen.png"},{"description":"","id":355349,"title":"Block Signal Connector","modId":461710,"url":"https://media.forgecdn.net/attachments/355/349/rspen-connector.png","thumbnailUrl":"https://media.forgecdn.net/attachments/thumbnails/355/349/310/172/rspen-connector.png"},{"description":"","id":355351,"title":"Quill Recipe","modId":461710,"url":"https://media.forgecdn.net/attachments/355/351/rspen-quill-recipe.png","thumbnailUrl":"https://media.forgecdn.net/attachments/thumbnails/355/351/310/172/rspen-quill-recipe.png"},{"description":"","id":443052,"title":"Redstone Logic Controller - Block","modId":461710,"url":"https://media.forgecdn.net/attachments/443/52/redstone-logic-control-1.png","thumbnailUrl":"https://media.forgecdn.net/attachments/thumbnails/443/52/310/172/redstone-logic-control-1.png"},{"description":"","id":552404,"title":"RLC keypad example","modId":461710,"url":"https://media.forgecdn.net/attachments/552/404/rlc-keypad-example.png","thumbnailUrl":"https://media.forgecdn.net/attachments/thumbnails/552/404/310/172/rlc-keypad-example.png"},{"description":"","id":357104,"title":"Overview Relays","modId":461710,"url":"https://media.forgecdn.net/attachments/357/104/2021-04-18-relays.png","thumbnailUrl":"https://media.forgecdn.net/attachments/thumbnails/357/104/310/172/2021-04-18-relays.png"}],"classId":6,"latestFilesIndexes":[{"filename":"redstonepen-1.21-neoforge-1.11.41.jar","releaseType":1,"gameVersion":"1.21","gameVersionTypeId":77784,"modLoader":6,"fileId":5764234},{"filename":"redstonepen-1.21-neoforge-1.11.41.jar","releaseType":1,"gameVersion":"1.21.1","gameVersionTypeId":77784,"modLoader":6,"fileId":5764234},{"filename":"redstonepen-1.21-fabric-1.11.41.jar","releaseType":1,"gameVersion":"1.21","gameVersionTypeId":77784,"modLoader":4,"fileId":5724712},{"filename":"redstonepen-1.21-fabric-1.11.41.jar","releaseType":1,"gameVersion":"1.21.1","gameVersionTypeId":77784,"modLoader":4,"fileId":5724712},{"filename":"redstonepen-1.20.4-neoforge-1.8.37.jar","releaseType":1,"gameVersion":"1.20.4","gameVersionTypeId":75125,"modLoader":6,"fileId":5584411},{"filename":"redstonepen-1.20.4-forge-1.8.33.jar","releaseType":1,"gameVersion":"1.20.4","gameVersionTypeId":75125,"modLoader":1,"fileId":5584134},{"filename":"redstonepen-1.21-fabric-1.11.36.jar","releaseType":2,"gameVersion":"1.21","gameVersionTypeId":77784,"modLoader":4,"fileId":5582094},{"filename":"redstonepen-1.20.6-fabric-1.10.33.jar","releaseType":1,"gameVersion":"1.20.6","gameVersionTypeId":75125,"modLoader":4,"fileId":5313361},{"filename":"redstonepen-1.20.5-fabric-1.9.33.jar","releaseType":1,"gameVersion":"1.20.5","gameVersionTypeId":75125,"modLoader":4,"fileId":5285432},{"filename":"redstonepen-1.20.4-fabric-1.8.32.jar","releaseType":1,"gameVersion":"1.20.4","gameVersionTypeId":75125,"modLoader":4,"fileId":5257190},{"filename":"redstonepen-1.20.1-neoforge-1.3.33.jar","releaseType":1,"gameVersion":"1.20.1","gameVersionTypeId":75125,"modLoader":1,"fileId":5242883},{"filename":"redstonepen-1.20.1-neoforge-1.3.33.jar","releaseType":1,"gameVersion":"1.20.1","gameVersionTypeId":75125,"modLoader":6,"fileId":5242883},{"filename":"redstonepen-1.19.2-forge-1.2.32.jar","releaseType":1,"gameVersion":"1.19.2","gameVersionTypeId":73407,"modLoader":1,"fileId":5242849},{"filename":"redstonepen-1.20.1-fabric-1.5.31.jar","releaseType":1,"gameVersion":"1.20.1","gameVersionTypeId":75125,"modLoader":4,"fileId":5241814},{"filename":"redstonepen-1.20.1-neoforge-1.3.32.jar","releaseType":3,"gameVersion":"1.20.1","gameVersionTypeId":75125,"modLoader":1,"fileId":5241473},{"filename":"redstonepen-1.20.1-neoforge-1.3.32.jar","releaseType":3,"gameVersion":"1.20.1","gameVersionTypeId":75125,"modLoader":6,"fileId":5241473},{"filename":"redstonepen-1.20.4-neoforge-1.8.29.jar","releaseType":2,"gameVersion":"1.20.4","gameVersionTypeId":75125,"modLoader":6,"fileId":5189420},{"filename":"redstonepen-1.20.2-fabric-1.6.28.jar","releaseType":2,"gameVersion":"1.20.2","gameVersionTypeId":75125,"modLoader":4,"fileId":5114576},{"filename":"redstonepen-1.20.4-fabric-1.8.27.jar","releaseType":2,"gameVersion":"1.20.4","gameVersionTypeId":75125,"modLoader":4,"fileId":5012166},{"filename":"redstonepen-1.20.3-fabric-1.7.24.jar","releaseType":1,"gameVersion":"1.20.3","gameVersionTypeId":75125,"modLoader":4,"fileId":4941182},{"filename":"redstonepen-1.20.2-fabric-1.6.24.jar","releaseType":1,"gameVersion":"1.20.2","gameVersionTypeId":75125,"modLoader":4,"fileId":4899815},{"filename":"redstonepen-1.19.4-fabric-1.4.23.jar","releaseType":1,"gameVersion":"1.19.4","gameVersionTypeId":73407,"modLoader":4,"fileId":4555715},{"filename":"redstonepen-1.19.4-forge-1.4.21.jar","releaseType":1,"gameVersion":"1.19.4","gameVersionTypeId":73407,"modLoader":1,"fileId":4555687},{"filename":"redstonepen-1.16.5-1.0.11.jar","releaseType":1,"gameVersion":"1.16.5","gameVersionTypeId":70886,"modLoader":1,"fileId":4329194},{"filename":"redstonepen-1.19.3-fabric-1.3.22.jar","releaseType":1,"gameVersion":"1.19.3","gameVersionTypeId":73407,"modLoader":4,"fileId":4329114},{"filename":"redstonepen-1.18.2-1.0.13.jar","releaseType":1,"gameVersion":"1.18.2","gameVersionTypeId":73250,"modLoader":1,"fileId":4327952},{"filename":"redstonepen-1.19.3-forge-1.3.20.jar","releaseType":1,"gameVersion":"1.19.3","gameVersionTypeId":73407,"modLoader":1,"fileId":4293320},{"filename":"redstonepen-1.19.2-fabric-1.2.18.jar","releaseType":1,"gameVersion":"1.19.2","gameVersionTypeId":73407,"modLoader":4,"fileId":3983447},{"filename":"redstonepen-1.19.2-forge-1.2.16.jar","releaseType":2,"gameVersion":"1.19.2","gameVersionTypeId":73407,"modLoader":1,"fileId":3970186},{"filename":"redstonepen-1.19.1-fabric-1.0.16.jar","releaseType":1,"gameVersion":"1.19.1","gameVersionTypeId":73407,"modLoader":4,"fileId":3921261},{"filename":"redstonepen-1.19-fabric-1.0.16.jar","releaseType":1,"gameVersion":"1.19","gameVersionTypeId":73407,"modLoader":4,"fileId":3921258},{"filename":"redstonepen-1.19.1-forge-1.1.15.jar","releaseType":2,"gameVersion":"1.19.1","gameVersionTypeId":73407,"modLoader":1,"fileId":3907628},{"filename":"redstonepen-1.19-forge-1.0.14.jar","releaseType":1,"gameVersion":"1.19","gameVersionTypeId":73407,"modLoader":1,"fileId":3904853},{"filename":"redstonepen-1.18.2-1.0.10-b3.jar","releaseType":2,"gameVersion":"1.18.2","gameVersionTypeId":73250,"modLoader":1,"fileId":3801323},{"filename":"redstonepen-1.18.1-1.0.9.jar","releaseType":1,"gameVersion":"1.18.1","gameVersionTypeId":73250,"modLoader":1,"fileId":3714078},{"filename":"redstonepen-1.16.5-1.0.8-b3.jar","releaseType":2,"gameVersion":"1.16.5","gameVersionTypeId":70886,"modLoader":1,"fileId":3675500},{"filename":"redstonepen-1.17.1-1.0.8.jar","releaseType":1,"gameVersion":"1.17.1","gameVersionTypeId":73242,"modLoader":1,"fileId":3652184},{"filename":"redstonepen-1.18.1-1.0.9-b2.jar","releaseType":2,"gameVersion":"1.18.1","gameVersionTypeId":73250,"modLoader":1,"fileId":3630421},{"filename":"redstonepen-1.16.5-1.0.6.jar","releaseType":1,"gameVersion":"1.16.4","gameVersionTypeId":70886,"modLoader":1,"fileId":3348960}],"dateCreated":"2021-03-26T07:08:01.673Z","logo":{"description":"","id":360034,"title":"637523392817214962.png","modId":461710,"url":"https://media.forgecdn.net/avatars/360/34/637523392817214962.png","thumbnailUrl":"https://media.forgecdn.net/avatars/thumbnails/360/34/256/256/637523392817214962.png"},"links":{"sourceUrl":"https://github.com/stfwi/redstonepen","issuesUrl":"https://github.com/stfwi/redstonepen/issues","websiteUrl":"https://www.curseforge.com/minecraft/mc-mods/redstone-pen","wikiUrl":""},"dateReleased":"2024-09-28T10:18:04.197Z","id":461710,"categories":[{"gameId":432,"classId":6,"name":"Redstone","dateModified":"2016-01-19T22:21:51.64Z","parentCategoryId":6,"id":4558,"iconUrl":"https://media.forgecdn.net/avatars/32/937/635888173116238506.png","slug":"redstone","url":"https://www.curseforge.com/minecraft/mc-mods/redstone","displayIndex":0,"class":false}],"slug":"redstone-pen","gameId":432,"summary":"Adds a pen to draw Redstone selectively and optimized, as well as signal repeating relays, and a Redstone logic controller.","latestFiles":[{"gameId":432,"fileName":"redstonepen-1.19.2-forge-1.2.16.jar","gameVersions":["1.19.2","Forge"],"displayName":"redstonepen-1.19.2-forge-1.2.16.jar","sortableGameVersions":[{"gameVersionPadded":"0000000001.0000000019.0000000002","gameVersion":"1.19.2","gameVersionReleaseDate":"2022-08-05T14:12:22.413Z","gameVersionName":"1.19.2","gameVersionTypeId":73407},{"gameVersionPadded":"0","gameVersion":"","gameVersionReleaseDate":"2022-10-01T00:00:00Z","gameVersionName":"Forge","gameVersionTypeId":68441}],"downloadUrl":"https://edge.forgecdn.net/files/3970/186/redstonepen-1.19.2-forge-1.2.16.jar","fileDate":"2022-09-05T19:18:51.547Z","exposeAsAlternative":null,"modId":461710,"modules":[{"name":"META-INF","fingerprint":1297454036},{"name":".gitversion-redstonepen","fingerprint":706064002},{"name":"assets","fingerprint":3071082134},{"name":"data","fingerprint":187951018},{"name":"logo.png","fingerprint":421868000},{"name":"pack.mcmeta","fingerprint":4078225031},{"name":"wile","fingerprint":1315345601}],"dependencies":[],"fileFingerprint":1422485707,"fileStatus":4,"releaseType":2,"hashes":[{"value":"3d2b927b570a058a2078b70c522b29eeadd2ca03","algo":1},{"value":"c1fa1a82c4fba533c81794f33e5bbbac","algo":2}],"parentProjectFileId":null,"alternateFileId":0,"id":3970186,"fileLength":457824,"downloadCount":647,"serverPackFileId":null,"available":false,"serverPack":false},{"gameId":432,"fileName":"redstonepen-1.20.4-neoforge-1.8.29.jar","gameVersions":["Client","NeoForge","1.20.4","Server"],"displayName":"redstonepen-1.20.4-neoforge-1.8.29.jar","sortableGameVersions":[{"gameVersionPadded":"0","gameVersion":"","gameVersionReleaseDate":"2022-12-08T00:00:00Z","gameVersionName":"Client","gameVersionTypeId":75208},{"gameVersionPadded":"0","gameVersion":"","gameVersionReleaseDate":"2023-07-25T00:00:00Z","gameVersionName":"NeoForge","gameVersionTypeId":68441},{"gameVersionPadded":"0000000001.0000000020.0000000004","gameVersion":"1.20.4","gameVersionReleaseDate":"2023-12-07T15:17:47.907Z","gameVersionName":"1.20.4","gameVersionTypeId":75125},{"gameVersionPadded":"0","gameVersion":"","gameVersionReleaseDate":"2022-12-08T00:00:00Z","gameVersionName":"Server","gameVersionTypeId":75208}],"downloadUrl":"https://edge.forgecdn.net/files/5189/420/redstonepen-1.20.4-neoforge-1.8.29.jar","fileDate":"2024-03-17T13:28:11.670Z","exposeAsAlternative":null,"modId":461710,"modules":[{"name":"META-INF","fingerprint":2411996007},{"name":"wile","fingerprint":1502000759},{"name":".gitversion-redstonepen","fingerprint":507594545},{"name":"assets","fingerprint":1446524921},{"name":"data","fingerprint":187951018},{"name":"pack.mcmeta","fingerprint":2111720944}],"dependencies":[],"fileFingerprint":3500213527,"fileStatus":4,"releaseType":2,"hashes":[{"value":"7b624c2813ad0c216937300a9ce91647d1520ffe","algo":1},{"value":"8262205a55aab732445e2cdec8509c6d","algo":2}],"parentProjectFileId":null,"alternateFileId":0,"id":5189420,"fileLength":450921,"downloadCount":12,"serverPackFileId":null,"available":false,"serverPack":false},{"gameId":432,"fileName":"redstonepen-1.20.1-neoforge-1.3.32.jar","gameVersions":["Client","NeoForge","1.20.1","Forge","Server"],"displayName":"redstonepen-1.20.1-neoforge-1.3.32.jar","sortableGameVersions":[{"gameVersionPadded":"0","gameVersion":"","gameVersionReleaseDate":"2022-12-08T00:00:00Z","gameVersionName":"Client","gameVersionTypeId":75208},{"gameVersionPadded":"0","gameVersion":"","gameVersionReleaseDate":"2023-07-25T00:00:00Z","gameVersionName":"NeoForge","gameVersionTypeId":68441},{"gameVersionPadded":"0000000001.0000000020.0000000001","gameVersion":"1.20.1","gameVersionReleaseDate":"2023-06-12T14:26:38.477Z","gameVersionName":"1.20.1","gameVersionTypeId":75125},{"gameVersionPadded":"0","gameVersion":"","gameVersionReleaseDate":"2022-10-01T00:00:00Z","gameVersionName":"Forge","gameVersionTypeId":68441},{"gameVersionPadded":"0","gameVersion":"","gameVersionReleaseDate":"2022-12-08T00:00:00Z","gameVersionName":"Server","gameVersionTypeId":75208}],"downloadUrl":"https://edge.forgecdn.net/files/5241/473/redstonepen-1.20.1-neoforge-1.3.32.jar","fileDate":"2024-04-06T21:12:56.760Z","exposeAsAlternative":null,"modId":461710,"modules":[{"name":"META-INF","fingerprint":2895166110},{"name":".gitversion-redstonepen","fingerprint":783320523},{"name":"assets","fingerprint":1203504063},{"name":"data","fingerprint":1187660494},{"name":"pack.mcmeta","fingerprint":3358670630},{"name":"wile","fingerprint":185844899}],"dependencies":[],"fileFingerprint":2662209486,"fileStatus":4,"releaseType":3,"hashes":[{"value":"af0e5b785c2460d19bbd01ef52f5dd8dbfc1de33","algo":1},{"value":"f9d003227fe2783d6dcc4ed2cd0f10bc","algo":2}],"parentProjectFileId":null,"alternateFileId":0,"id":5241473,"fileLength":472216,"downloadCount":100,"serverPackFileId":null,"available":false,"serverPack":false},{"gameId":432,"fileName":"redstonepen-1.21-fabric-1.11.36.jar","gameVersions":["1.21","Fabric","Client","Server"],"displayName":"redstonepen-1.21-fabric-1.11.36.jar","sortableGameVersions":[{"gameVersionPadded":"0000000001.0000000021","gameVersion":"1.21","gameVersionReleaseDate":"2024-06-14T00:00:00Z","gameVersionName":"1.21","gameVersionTypeId":77784},{"gameVersionPadded":"0","gameVersion":"","gameVersionReleaseDate":"2022-09-01T00:00:00Z","gameVersionName":"Fabric","gameVersionTypeId":68441},{"gameVersionPadded":"0","gameVersion":"","gameVersionReleaseDate":"2022-12-08T00:00:00Z","gameVersionName":"Client","gameVersionTypeId":75208},{"gameVersionPadded":"0","gameVersion":"","gameVersionReleaseDate":"2022-12-08T00:00:00Z","gameVersionName":"Server","gameVersionTypeId":75208}],"downloadUrl":"https://edge.forgecdn.net/files/5582/94/redstonepen-1.21-fabric-1.11.36.jar","fileDate":"2024-07-30T23:20:18.387Z","exposeAsAlternative":null,"modId":461710,"modules":[{"name":"META-INF","fingerprint":3770724246},{"name":".gitversion-redstonepen","fingerprint":1936751233},{"name":"LICENSE_redstonepen-1.21-fabric","fingerprint":2897836672},{"name":"assets","fingerprint":496325627},{"name":"data","fingerprint":554608718},{"name":"fabric.mod.json","fingerprint":1789356984},{"name":"pack.mcmeta","fingerprint":2644052382},{"name":"redstonepen-1.21-fabric-refmap.json","fingerprint":3884030195},{"name":"redstonepen.mixins.json","fingerprint":2959716935},{"name":"wile","fingerprint":24877006}],"dependencies":[],"fileFingerprint":4202654911,"fileStatus":4,"releaseType":2,"hashes":[{"value":"d016e464fff300cce316320733d67c195c2976b7","algo":1},{"value":"cb32fd52147c70663faad6990ce4adba","algo":2}],"parentProjectFileId":null,"alternateFileId":0,"id":5582094,"fileLength":483259,"downloadCount":52,"serverPackFileId":null,"available":false,"serverPack":false},{"gameId":432,"fileName":"redstonepen-1.20.4-forge-1.8.33.jar","gameVersions":["Client","Forge","1.20.4","Server"],"displayName":"redstonepen-1.20.4-forge-1.8.33.jar","sortableGameVersions":[{"gameVersionPadded":"0","gameVersion":"","gameVersionReleaseDate":"2022-12-08T00:00:00Z","gameVersionName":"Client","gameVersionTypeId":75208},{"gameVersionPadded":"0","gameVersion":"","gameVersionReleaseDate":"2022-10-01T00:00:00Z","gameVersionName":"Forge","gameVersionTypeId":68441},{"gameVersionPadded":"0000000001.0000000020.0000000004","gameVersion":"1.20.4","gameVersionReleaseDate":"2023-12-07T15:17:47.907Z","gameVersionName":"1.20.4","gameVersionTypeId":75125},{"gameVersionPadded":"0","gameVersion":"","gameVersionReleaseDate":"2022-12-08T00:00:00Z","gameVersionName":"Server","gameVersionTypeId":75208}],"downloadUrl":"https://edge.forgecdn.net/files/5584/134/redstonepen-1.20.4-forge-1.8.33.jar","fileDate":"2024-07-31T14:16:32.027Z","exposeAsAlternative":null,"modId":461710,"modules":[{"name":"META-INF","fingerprint":1445667913},{"name":".gitversion-redstonepen","fingerprint":1198446128},{"name":"assets","fingerprint":2338105077},{"name":"data","fingerprint":187951018},{"name":"pack.mcmeta","fingerprint":2644052382},{"name":"wile","fingerprint":510807487}],"dependencies":[],"fileFingerprint":1819967490,"fileStatus":4,"releaseType":1,"hashes":[{"value":"afe24752b6466effa74fa33f31e2ecbb71e933bb","algo":1},{"value":"91b0553d8fb884c6e9858e416d5d07b7","algo":2}],"parentProjectFileId":null,"alternateFileId":0,"id":5584134,"fileLength":461688,"downloadCount":166,"serverPackFileId":null,"available":false,"serverPack":false},{"gameId":432,"fileName":"redstonepen-1.21-fabric-1.11.41.jar","gameVersions":["1.21","Fabric","Client","1.21.1","Server"],"displayName":"redstonepen-1.21-fabric-1.11.41.jar","sortableGameVersions":[{"gameVersionPadded":"0000000001.0000000021","gameVersion":"1.21","gameVersionReleaseDate":"2024-06-14T00:00:00Z","gameVersionName":"1.21","gameVersionTypeId":77784},{"gameVersionPadded":"0","gameVersion":"","gameVersionReleaseDate":"2022-09-01T00:00:00Z","gameVersionName":"Fabric","gameVersionTypeId":68441},{"gameVersionPadded":"0","gameVersion":"","gameVersionReleaseDate":"2022-12-08T00:00:00Z","gameVersionName":"Client","gameVersionTypeId":75208},{"gameVersionPadded":"0000000001.0000000021.0000000001","gameVersion":"1.21.1","gameVersionReleaseDate":"2024-08-08T15:17:53.787Z","gameVersionName":"1.21.1","gameVersionTypeId":77784},{"gameVersionPadded":"0","gameVersion":"","gameVersionReleaseDate":"2022-12-08T00:00:00Z","gameVersionName":"Server","gameVersionTypeId":75208}],"downloadUrl":"https://edge.forgecdn.net/files/5724/712/redstonepen-1.21-fabric-1.11.41.jar","fileDate":"2024-09-15T09:16:43.863Z","exposeAsAlternative":null,"modId":461710,"modules":[{"name":"META-INF","fingerprint":3819136317},{"name":".gitversion-redstonepen","fingerprint":4116540549},{"name":"LICENSE_redstonepen-1.21-fabric","fingerprint":2897836672},{"name":"assets","fingerprint":2041899519},{"name":"data","fingerprint":882923231},{"name":"fabric.mod.json","fingerprint":277697538},{"name":"pack.mcmeta","fingerprint":2644052382},{"name":"redstonepen-1.21-fabric-refmap.json","fingerprint":3884030195},{"name":"redstonepen.mixins.json","fingerprint":2959716935},{"name":"wile","fingerprint":1568584454}],"dependencies":[],"fileFingerprint":3731434190,"fileStatus":4,"releaseType":1,"hashes":[{"value":"7a4d99fc9b305bc23970fae582bf57ccf93664a5","algo":1},{"value":"d24d9671fc5386a6513da4e51ac448fd","algo":2}],"parentProjectFileId":null,"alternateFileId":0,"id":5724712,"fileLength":513198,"downloadCount":1020,"serverPackFileId":null,"available":false,"serverPack":false},{"gameId":432,"fileName":"redstonepen-1.21-neoforge-1.11.41.jar","gameVersions":["1.21","Client","NeoForge","1.21.1","Server"],"displayName":"redstonepen-1.21-neoforge-1.11.41.jar","sortableGameVersions":[{"gameVersionPadded":"0000000001.0000000021","gameVersion":"1.21","gameVersionReleaseDate":"2024-06-14T00:00:00Z","gameVersionName":"1.21","gameVersionTypeId":77784},{"gameVersionPadded":"0","gameVersion":"","gameVersionReleaseDate":"2022-12-08T00:00:00Z","gameVersionName":"Client","gameVersionTypeId":75208},{"gameVersionPadded":"0","gameVersion":"","gameVersionReleaseDate":"2023-07-25T00:00:00Z","gameVersionName":"NeoForge","gameVersionTypeId":68441},{"gameVersionPadded":"0000000001.0000000021.0000000001","gameVersion":"1.21.1","gameVersionReleaseDate":"2024-08-08T15:17:53.787Z","gameVersionName":"1.21.1","gameVersionTypeId":77784},{"gameVersionPadded":"0","gameVersion":"","gameVersionReleaseDate":"2022-12-08T00:00:00Z","gameVersionName":"Server","gameVersionTypeId":75208}],"downloadUrl":"https://edge.forgecdn.net/files/5764/234/redstonepen-1.21-neoforge-1.11.41.jar","fileDate":"2024-09-28T10:18:04.197Z","exposeAsAlternative":null,"modId":461710,"modules":[{"name":"META-INF","fingerprint":4008073787},{"name":"wile","fingerprint":1754279881},{"name":".gitversion-redstonepen","fingerprint":1421776383},{"name":"assets","fingerprint":1192708065},{"name":"data","fingerprint":882923231},{"name":"pack.mcmeta","fingerprint":2644052382},{"name":"redstonepen.mixins.json","fingerprint":4024380309}],"dependencies":[],"fileFingerprint":258667895,"fileStatus":4,"releaseType":1,"hashes":[{"value":"d6bef4ac25c80de70714b77bac29b3a6f8fd1915","algo":1},{"value":"add93a1c7caf9eff2d04d768a34c5d7a","algo":2}],"parentProjectFileId":null,"alternateFileId":0,"id":5764234,"fileLength":515381,"downloadCount":226636,"serverPackFileId":null,"available":false,"serverPack":false}],"dateModified":"2024-09-28T10:22:57.27Z","gamePopularityRank":1095,"thumbsUpCount":0,"name":"Redstone Pen","mainFileId":5764234,"primaryCategoryId":4558,"downloadCount":6248829,"status":4,"authors":[{"name":"wilechaote","id":51451694,"url":"https://www.curseforge.com/members/wilechaote"}],"featured":false,"available":false}